LICENSE
MANIFEST.in
README.rst
pyproject.toml
setup.cfg
setup.py
account/__init__.py
account/admin.py
account/apps.py
account/models.py
account/tests.py
account/urls.py
account/views.py
account/migrations/__init__.py
account/python/__init__.py
account/python/form.py
account/python/smtp.py
account/python/static_messages.py
jnunes_accounts.egg-info/PKG-INFO
jnunes_accounts.egg-info/SOURCES.txt
jnunes_accounts.egg-info/dependency_links.txt
jnunes_accounts.egg-info/requires.txt
jnunes_accounts.egg-info/top_level.txt